catsay/__init__.py
catsay/cat_art.py
catsay/cli.py
catsay_cli-1.0.0.dist-info/licenses/LICENSE
catsay_cli-1.0.0.dist-info/METADATA
catsay_cli-1.0.0.dist-info/WHEEL
catsay_cli-1.0.0.dist-info/entry_points.txt
catsay_cli-1.0.0.dist-info/top_level.txt
catsay_cli-1.0.0.dist-info/RECORD
