Metadata-Version: 2.4
Name: catsay-cli
Version: 1.0.0
Summary: A fun CLI tool that prints cat ASCII art with your message.
Author-email: Mahdi <mirshafieemahdi001@gmail.com>
License-Expression: MIT
Requires-Python: >=3.7
License-File: LICENSE
Requires-Dist: rich>=13.0.0
Dynamic: license-file
